{"color":"RED","isTrashed":false,"isPinned":true,"isArchived":false,"textContent":"eistertrunlandesmeister auswählen Was erwartet dich in diesem Video  (Sportwettstrategie auf dem prüfstand)RookieBilanz zehn Mannschaften die den meistertitel in ihrem jeweiligen Land geholt haben wie wäre die kombinationswette dazu wöchentlich ausgegangen wie wäre die Bilanz für jedes Team als einzelwette mit und ohne wettsteuer ausgegangen inklusive Vergleich wie wäre Bilanz als einzelwette mit pinnacle Open und closing odds für einen flachen und dynamischen Einsatz gewesen inklusive Vergleich wie wäre die Bilanz mit Turner Bett Sieg Favorit ausgegangenAmateure wie wäre die Bilanz für Trading auf pinnacle mit den open odd für den Favoriten und closing und x und Underdog ausgegangen wie wäre die Bilanz gegen den Favoriten als auswärtsteam mit Ansteigen der Quote im Zusammenhang doppelt Chance x und Sieg an der dog ausgegangen woher stammen die Daten dieser Analyse wie erstellt man eine solche Analyse für sich selbst woher kann man diesen Excel Sheet kostenlos herunterladen\"Hallo zurück auf meinem Bildschirm bevor wir hier uns in die Zahlen stürzen möchte ich dir kurz zeigen was dich in diesem Video erwartet da ist es ja ein sehr umfangreiches Video wird und zwar beginnen wir mit der Bilanz von den zehn Mannschaften die den meistertitel von ihren jeweiligen Ländern geholt haben dann schauen wir uns an wie die kombinationswetten dazu wöchentlich ausgesehen hätten in weiterer Folge für jedes einzelne Team und schauen uns das ganz genau an wie hätte das mit einzelbettensteuer ausgesehen dann wie wäre die Bilanz als einzelwetter mit den panical Open und closingorts für einen flachen und einen dynamischen Einsatz gewesen das zeige ich euch inklusive einen Vergleich welche quotenbewegungen hat es gegeben zwischen den Open und closing von paniker dann gehen wir weiter und schauen uns dann auch die Strategie an wie wäre die Bilanz mit dr Bett Sieg Favorit ausgegangen wenn wir das die gesamte Saison durchgespielt hätten im nächsten Abschnitt haben wir dann schon für fortgeschrittene ähm wie wäre die Bilanz denn gewesen wenn wir für mit peinecke nur getradet hätten das heißt wir hätten hier den Vergleich angestrebt von der Open Art bei peinecke am vom Favoriten wenn wir auf diesen dann Geld gesetzt hätten und dann erst die closingort von x und den Underdog dann abgesichert hätten ob wir damit Erfolg gehabt hätten ähm ja dann schauen wir uns auch an wie die Bilanz gegen den Favoriten ausgegangen wäre wenn der Favorit als auswärtsteam angetreten ist und hier zum Beispiel wie erkennen dass die Quote ansteigt also von der startquote zur closingort und wenn wir dann anstatt auf den Favoriten auf die Doppel Chance x und Sieg Underdog gespielt hätten dann zeige ich euch auch noch woher ich diese ganzen Daten diese Analyse habe wie auch du selber solche Analysen für dich dann in weiterer Folge erstellen kannst und ganz zum Schluss noch wo du dieses Excel schied kostenlos dir ansehen und herunterladen kannst \"","title":"Meistertrun system/analyse","userEditedTimestampUsec":1773521141938000,"createdTimestampUsec":1671846163860000,"textContentHtml":"<p dir=\"ltr\" style=\"line-height:1.38;margin-top:0.0pt;margin-bottom:0.0pt;\"><span style=\"font-size:7.2pt;font-family:'Google Sans';color:#000000;background-color:transparent;font-weight:400;font-style:normal;font-variant:normal;text-decoration:none;vertical-align:baseline;white-space:pre;white-space:pre-wrap;\">eistertrunlandesmeister auswählen Was erwartet dich in diesem Video&nbsp; (Sportwettstrategie auf dem prüfstand)RookieBilanz zehn Mannschaften die den meistertitel in ihrem jeweiligen Land geholt haben wie wäre die kombinationswette dazu wöchentlich ausgegangen wie wäre die Bilanz für jedes Team als einzelwette mit und ohne wettsteuer ausgegangen inklusive Vergleich wie wäre Bilanz als einzelwette mit pinnacle Open und closing odds für einen flachen und dynamischen Einsatz gewesen inklusive Vergleich wie wäre die Bilanz mit Turner Bett Sieg Favorit ausgegangenAmateure wie wäre die Bilanz für Trading auf pinnacle mit den open odd für den Favoriten und closing und x und Underdog ausgegangen wie wäre die Bilanz gegen den Favoriten als auswärtsteam mit Ansteigen der Quote im Zusammenhang doppelt Chance x und Sieg an der dog ausgegangen woher stammen die Daten dieser Analyse wie erstellt man eine solche Analyse für sich selbst woher kann man diesen Excel Sheet kostenlos herunterladen&quot;Hallo zurück auf meinem Bildschirm bevor wir hier uns in die Zahlen stürzen möchte ich dir kurz zeigen was dich in diesem Video erwartet da ist es ja ein sehr umfangreiches Video wird und zwar beginnen wir mit der Bilanz von den zehn Mannschaften die den meistertitel von ihren jeweiligen Ländern geholt haben dann schauen wir uns an wie die kombinationswetten dazu wöchentlich ausgesehen hätten in weiterer Folge für jedes einzelne Team und schauen uns das ganz genau an wie hätte das mit einzelbettensteuer ausgesehen dann wie wäre die Bilanz als einzelwetter mit den panical Open und closingorts für einen flachen und einen dynamischen Einsatz gewesen das zeige ich euch inklusive einen Vergleich welche quotenbewegungen hat es gegeben zwischen den Open und closing von paniker dann gehen wir weiter und schauen uns dann auch die Strategie an wie wäre die Bilanz mit dr Bett Sieg Favorit ausgegangen wenn wir das die gesamte Saison durchgespielt hätten im nächsten Abschnitt haben wir dann schon für fortgeschrittene ähm wie wäre die Bilanz denn gewesen wenn wir für mit peinecke nur getradet hätten das heißt wir hätten hier den Vergleich angestrebt von der Open Art bei peinecke am vom Favoriten wenn wir auf diesen dann Geld gesetzt hätten und dann erst die closingort von x und den Underdog dann abgesichert hätten ob wir damit Erfolg gehabt hätten ähm ja dann schauen wir uns auch an wie die Bilanz gegen den Favoriten ausgegangen wäre wenn der Favorit als auswärtsteam angetreten ist und hier zum Beispiel wie erkennen dass die Quote ansteigt also von der startquote zur closingort und wenn wir dann anstatt auf den Favoriten auf die Doppel Chance x und Sieg Underdog gespielt hätten dann zeige ich euch auch noch woher ich diese ganzen Daten diese Analyse habe wie auch du selber solche Analysen für dich dann in weiterer Folge erstellen kannst und ganz zum Schluss noch wo du dieses Excel schied kostenlos dir ansehen und herunterladen kannst &quot;<\/span><\/p>","labels":[{"name":"7ven"}]}